setup.py
uws/__init__.py
uws/UWS/__init__.py
uws/UWS/client.py
uws/UWS/connection.py
uws/UWS/errors.py
uws/UWS/models.py
uws/UWS/tests/__init__.py
uws/UWS/tests/test_base.py
uws/UWS/tests/test_connection.py
uws/UWS/tests/test_models.py
uws/cli/__init__.py
uws/cli/cli_parser.py
uws/cli/main.py
uws/lib/__init__.py
uws/lib/terminalsize/__init__.py
uws/lib/terminalsize/terminalsize.py
uws_client.egg-info/PKG-INFO
uws_client.egg-info/SOURCES.txt
uws_client.egg-info/dependency_links.txt
uws_client.egg-info/entry_points.txt
uws_client.egg-info/requires.txt
uws_client.egg-info/top_level.txt