Metadata-Version: 1.1
Name: uws-client
Version: 1.1.5
Summary: a command line client for IVOA UWS services, plus models for development
Home-page: http://github.com/aipescience/uws-client/
Author: AIP E-Science
Author-email: escience@aip.de
License: Apache License (2.0)
Download-URL: http://github.com/aipescience/uws-client/archive/1.1.5.tar.gz
Platform: UNKNOWN
Classifier: Development Status :: 4 - Beta
Classifier: Environment :: Console
Classifier: Intended Audience :: Science/Research
Classifier: License :: OSI Approved :: Apache Software License
Classifier: Operating System :: OS Independent
Classifier: Programming Language :: Python :: 2.7
